xdeploy/__init__.py
xdeploy/base/__init__.py
xdeploy/base/build_onnx_engine.py
xdeploy/base/build_ov_engine.py
xdeploy/base/build_tensorrt_engine.py
xdeploy/base/tensor.py
xdeploy/base/yolo.py
xdeploy/classification/__init__.py
xdeploy/classification/yolo11_cls.py
xdeploy/classification/yolov8_cls.py
xdeploy/detection/__init__.py
xdeploy/detection/rtdetr.py
xdeploy/detection/yolo11.py
xdeploy/detection/yolov10.py
xdeploy/detection/yolov8.py
xdeploy/obb/__init__.py
xdeploy/obb/yolo11_obb.py
xdeploy/obb/yolov8_obb.py
xdeploy/ocr/__init__.py
xdeploy/ocr/ppocr/__init__.py
xdeploy/ocr/ppocr/ic15_dict.txt
xdeploy/ocr/ppocr/ppocr_keys_v1.txt
xdeploy/ocr/ppocr/predict_det.py
xdeploy/ocr/ppocr/predict_rec.py
xdeploy/ocr/ppocr/predict_system.py
xdeploy/ocr/ppocr/utility.py
xdeploy/ocr/ppocr/utils.py
xdeploy/pose/__init__.py
xdeploy/pose/yolo11_pose.py
xdeploy/pose/yolov8_pose.py
xdeploy/results/__init__.py
xdeploy/results/classify_result.py
xdeploy/results/detection_result.py
xdeploy/results/instance_seg_result.py
xdeploy/results/obb_result.py
xdeploy/results/ocr_result.py
xdeploy/results/pose_result.py
xdeploy/results/semantic_seg_result.py
xdeploy/segmentation/__init__.py
xdeploy/segmentation/instance/__init__.py
xdeploy/segmentation/instance/yolo11_seg.py
xdeploy/segmentation/instance/yolov8_seg.py
xdeploy/segmentation/semantic/__init__.py
xdeploy/segmentation/semantic/paddleseg.py
xdeploy/utils/__init__.py
xdeploy/utils/data_load.py
xdeploy/utils/visualize.py
xdeploy-0.1.6.dist-info/METADATA
xdeploy-0.1.6.dist-info/WHEEL
xdeploy-0.1.6.dist-info/licenses/LICENSE
xdeploy-0.1.6.dist-info/RECORD
