Metadata-Version: 2.4
Name: xdeploy
Version: 0.1.6
Summary: 视觉 AI 模型部署框架
License-File: LICENSE
Classifier: Programming Language :: Python :: 3
Classifier: Programming Language :: Python :: 3.8
Classifier: Programming Language :: Python :: 3.9
Classifier: Programming Language :: Python :: 3.10
Classifier: Programming Language :: Python :: 3.11
Classifier: Programming Language :: Python :: 3.12
Requires-Python: >=3.8
Requires-Dist: numpy>=1.24.4
Requires-Dist: onnxruntime<1.20.0; python_version <= '3.9'
Requires-Dist: onnxruntime>=1.20.1; python_version > '3.9'
Requires-Dist: opencv-python>=4.11.0.86
Requires-Dist: pillow>=10.4.0
Requires-Dist: pyclipper>=1.3.0.post6
Requires-Dist: shapely>=2.0.0
